pypkgs_gt/__init__.py
pypkgs_gt/pypkgs_gt.py
pypkgs_gt-0.1.0.dist-info/LICENSE
pypkgs_gt-0.1.0.dist-info/WHEEL
pypkgs_gt-0.1.0.dist-info/METADATA
pypkgs_gt-0.1.0.dist-info/RECORD
